filee/__init__.py
filee/hasher.py
filee/main.py
filee/models.py
filee/settings.py
filee/testing.py
filee-0.0.5.dist-info/LICENSE
filee-0.0.5.dist-info/METADATA
filee-0.0.5.dist-info/WHEEL
filee-0.0.5.dist-info/entry_points.txt
filee-0.0.5.dist-info/top_level.txt
filee-0.0.5.dist-info/RECORD
