Metadata-Version: 2.1
Name: filee
Version: 0.0.5
Summary: A command to save / load files with JSON input / output.
Home-page: UNKNOWN
License: UNKNOWN
Platform: UNKNOWN
Requires-Dist: Click
